rainbowline/__init__.py
rainbowline/rainbowline.py
rainbowline-0.0.1.dist-info/METADATA
rainbowline-0.0.1.dist-info/WHEEL
rainbowline-0.0.1.dist-info/licenses/LICENSE
rainbowline-0.0.1.dist-info/RECORD
