Metadata-Version: 2.1
Name: rainbowline
Version: 0.0.1
Summary: A simple library for plotting lines with color gradients
Project-URL: Homepage, https://github.com/patmalcolm91/rainbowline
Project-URL: Bug Tracker, https://github.com/patmalcolm91/rainbowline/issues
Author-email: Patrick Malcolm <patmalcolm91@gmail.com>
License: MIT License
Classifier: License :: OSI Approved :: MIT License
Classifier: Operating System :: OS Independent
Classifier: Programming Language :: Python :: 3
Requires-Python: >=3.7
